<?xml version="1.0" encoding="UTF-8" ?>    

      
	<device xmlns:xi="http://www.w3.org/2001/XInclude" name="icub_fake_battery" type="fakeBattery">  

	<group name="GENERAL">    
		<param name="name">  icub_fake_battery  </param>   
		<param name="thread_period">        0.1 </param>
		<param name="charge">             100.0 </param>
		<param name="voltage">             30.0 </param>
		<param name="current">              3.0 </param>
		<param name="temperature">         20.0 </param>
	</group>             
		
	</device>    
          
